assi/__init__.py
assi/assi.py
assi-1.0.2.dist-info/METADATA
assi-1.0.2.dist-info/WHEEL
assi-1.0.2.dist-info/top_level.txt
assi-1.0.2.dist-info/RECORD
